{"R:-ry":{"deep_origin":"Old French -erie, suffix indicating place, condition, or collective activity","derivatives":["quarry","bakery","gallery","jewelry"],"id":"R:-ry","lookup_count":0,"meaning":"表场所、行业、状态或集合","segment":"-ry","type":"后缀","updated_at":1779475517057},"R:ry":{"deep_origin":"形容词后缀，意为“有……性质的”或“处于……状态的”。","derivatives":["angry","cavalry","machinery","bravery","model-registry","worry","marry","registry","ministry","industry","quarry","bakery","gallery","jewelry"],"id":"R:ry","lookup_count":0,"meaning":"表形容词","segment":"-ry","type":"后缀","updated_at":1779840349724}}